budget/__init__.py
budget/admin.py
budget/apps.py
budget/authentication.py
budget/celery.py
budget/forms.py
budget/github.py
budget/serializers.py
budget/signals.py
budget/tests.py
budget/urls.py
budget/views.py
budget/viewsets.py
budget/widgets.py
budget/management/__init__.py
budget/management/commands/__init__.py
budget/management/commands/budget_board_status.py
budget/migrations/0001_initial.py
budget/migrations/__init__.py
budget/models/__init__.py
budget/models/board.py
budget/models/column.py
budget/models/project.py
budget/models/slugged.py
budget/models/tag.py
budget/models/todo.py
budget/models/type.py
budget/static/budget/css/main-board-app.css
budget/static/budget/css/main-board-list.css
budget/static/budget/fonts/rw-widgets.ttf
budget/static/budget/fonts/rw-widgets.woff
budget/static/budget/fonts/rw-widgets.woff2
budget/static/budget/images/grid.png
budget/static/budget/js/main-board-app.js
budget/static/budget/js/main-board-list.js
budget/tasks/__init__.py
budget/tasks/github.py
budget/tasks/slack/__init__.py
budget/tasks/slack/board.py
budget/tasks/slack/project.py
budget/templates/budget/base.html
budget/templates/budget/board.html
budget/templates/budget/home.html
budget/templates/budget/override_board.html
budget/templates/budget/override_home.html
budget/templatetags/__init__.py
budget/templatetags/budget_markdown_tags.py
django_kanban_budget-0.1.4.dist-info/METADATA
django_kanban_budget-0.1.4.dist-info/RECORD
django_kanban_budget-0.1.4.dist-info/WHEEL
django_kanban_budget-0.1.4.dist-info/top_level.txt
