Metadata-Version: 2.1
Name: django-kanban-budget
Version: 0.1.4
Summary: A Kanban-style project management app for developer-journalists in newsrooms. (Not about $$$.)
Home-page: https://github.com/The-Politico/django-kanban-budget
Author: UNKNOWN
Author-email: UNKNOWN
License: MIT
Platform: UNKNOWN
Classifier: Environment :: Web Environment
Classifier: Framework :: Django
Classifier: Intended Audience :: Developers
Classifier: License :: OSI Approved :: MIT License
Classifier: Operating System :: OS Independent
Classifier: Programming Language :: Python
Classifier: Programming Language :: Python :: 3
Classifier: Programming Language :: Python :: 3.4
Classifier: Programming Language :: Python :: 3.5
Classifier: Topic :: Internet :: WWW/HTTP
Classifier: Topic :: Internet :: WWW/HTTP :: Dynamic Content
Requires-Dist: django (>=2.1.0)
Requires-Dist: djangorestframework (>=3.7.7)
Requires-Dist: django-filter (>=2.0.0.dev1)
Requires-Dist: django-uuslug
Requires-Dist: celery
Requires-Dist: markdown
Requires-Dist: PyGithub
Requires-Dist: slacker
